Workbook
Name coyname: 'Cover page'!$I$6

Sheet Cover page
B2: Table of content | F2: ABC BOTTLE WATER
A4: Guide
E5: Company Information
A6: Output | F6: Company Name | I6: ABC BOTTLE WATER
B7: Income statement | F7: Industry | I7: Manufacturing
B8: Financial position
B9: Cash flow statement | E9: Modeller Information
F10: Modeller Name | I10: Yisau OI
A11: Calculation
B12: Operation | E12: Date Information
F13: Forecast period | I13: 5
A14: Model | F14: Forecast start year | I14: 2025
B15: Input | F15: Forecast End year | I15: =I14+4 -> 2029
F16: Forecast start date | I16: =DATE(I14,1,1) -> 45658
F17: Forecast End date | I17: =DATE(I15,1,1) -> 47119
E21: Currency
F22: Naira | I22: =_xlfn.UNICHAR(8358) -> ₦

Sheet Guide
A1: =coyname -> ABC BOTTLE WATER | H1: years | I1: ='Cover page'!I14 -> 2025 | J1: =I1+1 -> 2026 | K1: =J1+1 -> 2027 | L1: =K1+1 -> 2028 | M1: =L1+1 -> 2029
A2: 3-statement Model | H2: Start date | I2: ='Cover page'!I16 -> 45658 | J2: =EDATE(I2,12) -> 46023 | K2: =EDATE(J2,12) -> 46388 | L2: =EDATE(K2,12) -> 46753 | M2: =EDATE(L2,12) -> 47119
A3: All figures are in #(Naira) | H3: End date | I3: =DATE(I1,12,31) -> 46022 | J3: =DATE(J1,12,31) -> 46387 | K3: =DATE(K1,12,31) -> 46752 | L3: =DATE(L1,12,31) -> 47118 | M3: =DATE(M1,12,31) -> 47483
H4: Year Counter | I4: 1 | J4: =I4+1 -> 2 | K4: =J4+1 -> 3 | L4: =K4+1 -> 4 | M4: =L4+1 -> 5
A7: Model Guide
B8: Input cells | D8: 12345
B9: operation | D9: 12345
B10: Linked cells | D10: 12345
B11: Headings | D11: Abcde
B12: Key data | D12: abcde
B13: Sub-Total | D13: 12345
B14: Total | D14: 12345

Sheet Output>>
A1: =coyname -> ABC BOTTLE WATER | H1: years | I1: ='Cover page'!I14 -> 2025 | J1: =I1+1 -> 2026 | K1: =J1+1 -> 2027 | L1: =K1+1 -> 2028 | M1: =L1+1 -> 2029
A2: 3-statement Model | H2: Start date | I2: ='Cover page'!I16 -> 45658 | J2: =EDATE(I2,12) -> 46023 | K2: =EDATE(J2,12) -> 46388 | L2: =EDATE(K2,12) -> 46753 | M2: =EDATE(L2,12) -> 47119
A3: All figures are in #(Naira) | H3: End date | I3: =DATE(I1,12,31) -> 46022 | J3: =DATE(J1,12,31) -> 46387 | K3: =DATE(K1,12,31) -> 46752 | L3: =DATE(L1,12,31) -> 47118 | M3: =DATE(M1,12,31) -> 47483
H4: Year Counter | I4: 1 | J4: =I4+1 -> 2 | K4: =J4+1 -> 3 | L4: =K4+1 -> 4 | M4: =L4+1 -> 5

Sheet FS
A1: =coyname -> ABC BOTTLE WATER | H1: years | I1: ='Cover page'!I14 -> 2025 | J1: =I1+1 -> 2026 | K1: =J1+1 -> 2027 | L1: =K1+1 -> 2028 | M1: =L1+1 -> 2029
A2: 3-statement Model | H2: Start date | I2: ='Cover page'!I16 -> 45658 | J2: =EDATE(I2,12) -> 46023 | K2: =EDATE(J2,12) -> 46388 | L2: =EDATE(K2,12) -> 46753 | M2: =EDATE(L2,12) -> 47119
A3: All figures are in #(Naira) | H3: End date | I3: =DATE(I1,12,31) -> 46022 | J3: =DATE(J1,12,31) -> 46387 | K3: =DATE(K1,12,31) -> 46752 | L3: =DATE(L1,12,31) -> 47118 | M3: =DATE(M1,12,31) -> 47483
H4: Year Counter | I4: 1 | J4: =I4+1 -> 2 | K4: =J4+1 -> 3 | L4: =K4+1 -> 4 | M4: =L4+1 -> 5
A5: SCENERIO | C5: Best Case
C6: Base Case
C7: Worse Case
A9: Income statement
B10: Revenue | I10: =Operation!J13 -> 54000000 | J10: =Operation!K13 -> 56700000 | K10: =Operation!L13 -> 61321050 | L10: =Operation!M13 -> 63654000 | M10: =Operation!N13 -> 65563620
B11: Direct Cost | I11: =Operation!J22 -> 34200000 | J11: =Operation!K22 -> 36987300 | K11: =Operation!L22 -> 40001765 | L11: =Operation!M22 -> 41523626 | M11: =Operation!N22 -> 42769335
B12: Gross Profit | I12: =I10-I11 -> 19800000 | J12: =J10-J11 -> 19712700 | K12: =K10-K11 -> 21319285 | L12: =L10-L11 -> 22130374 | M12: =M10-M11 -> 22794285
B14: Operating expenses | I14: =Operation!J38 -> 13386000 | J14: =Operation!K38 -> 13386000 | K14: =Operation!L38 -> 13386000 | L14: =Operation!M38 -> 13386000 | M14: =Operation!N38 -> 13386000
B15: EBITDA | I15: =I12-I14 -> 6414000 | J15: =J12-J14 -> 6326700 | K15: =K12-K14 -> 7933285 | L15: =L12-L14 -> 8744374 | M15: =M12-M14 -> 9408285.2
B17: D&A | I17: =Operation!J64 -> 2600000 | J17: =Operation!K64 -> 2600000 | K17: =Operation!L64 -> 2600000 | L17: =Operation!M64 -> 2600000 | M17: =Operation!N64 -> 2600000
B18: EBIT | I18: =I15-I17 -> 3814000 | J18: =J15-J17 -> 3726700 | K18: =K15-K17 -> 5333285 | L18: =L15-L17 -> 6144374 | M18: =M15-M17 -> 6808285.2
B19: Interest expenses | I19: =I97 -> 1600000 | J19: =J97 -> 1280000 | K19: =K97 -> 960000 | L19: =L97 -> 640000 | M19: =M97 -> 320000
B21: EBT | I21: =I18-I19 -> 2214000 | J21: =J18-J19 -> 2446700 | K21: =K18-K19 -> 4373285 | L21: =L18-L19 -> 5504374 | M21: =M18-M19 -> 6488285.2
B22: Taxes | I22: =Operation!J77 -> 708480 | J22: =Operation!K77 -> 782944 | K22: =Operation!L77 -> 1399451.2 | L22: =Operation!M77 -> 1761399.7 | M22: =Operation!N77 -> 2076251.3
B23: Net Income | I23: =I21-I22 -> 1505520 | J23: =J21-J22 -> 1663756 | K23: =K21-K22 -> 2973833.8 | L23: =L21-L22 -> 3742974.3 | M23: =M21-M22 -> 4412033.9
B25: Retained Earnings
B26: Opening bal | I26: 0 | J26: =I29 -> 1279692 | K26: =J29 -> 2693884.6 | L26: =K29 -> 5221643.4 | M26: =L29 -> 8403171.5
B27: add: Net Income | I27: =I23 -> 1505520 | J27: =J23 -> 1663756 | K27: =K23 -> 2973833.8 | L27: =L23 -> 3742974.3 | M27: =M23 -> 4412033.9
B28: Less: Dividend | I28: =Operation!J81 -> 225828 | J28: =Operation!K81 -> 249563.4 | K28: =Operation!L81 -> 446075.08 | L28: =Operation!M81 -> 561446.15 | M28: =Operation!N81 -> 661805.09
B29: closing Bal | I29: =I26+I27-I28 -> 1279692 | J29: =J26+J27-J28 -> 2693884.6 | K29: =K26+K27-K28 -> 5221643.4 | L29: =L26+L27-L28 -> 8403171.5 | M29: =M26+M27-M28 -> 12153400
A33: Statement of Financial Position
B34: Assets
B35: PP&E | I35: =Operation!J65 -> 10400000 | J35: =Operation!K65 -> 7800000 | K35: =Operation!L65 -> 5200000 | L35: =Operation!M65 -> 2600000 | M35: =Operation!N65 -> 0
B36: Non - Current Asset | I36: =SUM(I35) -> 10400000 | J36: =SUM(J35) -> 7800000 | K36: =SUM(K35) -> 5200000 | L36: =SUM(L35) -> 2600000 | M36: =SUM(M35) -> 0
B38: Receivables | I38: =Operation!J68 -> 3698630.1 | J38: =Operation!K68 -> 3883561.6 | K38: =Operation!L68 -> 4200071.9 | L38: =Operation!M68 -> 4359863 | M38: =Operation!N68 -> 4490658.9
B39: Inventory | I39: =Operation!J70 -> 2810958.9 | J39: =Operation!K70 -> 3040052.1 | K39: =Operation!L70 -> 3287816.3 | L39: =Operation!M70 -> 3412900.8 | M39: =Operation!N70 -> 3515287.8
B40: Cash | I40: =I75 -> 1705445.4 | J40: =J75 -> 4026343.8 | K40: =K75 -> 7336698 | L40: =L75 -> 11408469 | M40: =M75 -> 16068857
B41: Total asset | I41: =SUM(I36:I40) -> 18615034 | J41: =SUM(J36:J40) -> 18749957 | K41: =SUM(K36:K40) -> 20024586 | L41: =SUM(L36:L40) -> 21781233 | M41: =SUM(M36:M40) -> 24074803
B43: Liabilities & Equity
B44: Trade Payables | I44: =Operation!J72 -> 3935342.5 | J44: =Operation!K72 -> 4256072.9 | K44: =Operation!L72 -> 4602942.8 | L44: =Operation!M72 -> 4778061.1 | M44: =Operation!N72 -> 4921402.9
B45: Revolver | I45: 0 | J45: 0 | K45: 0 | L45: 0 | M45: 0
B46: Long term debt | I46: =Operation!J50 -> 6400000 | J46: =Operation!K50 -> 4800000 | K46: =Operation!L50 -> 3200000 | L46: =Operation!M50 -> 1600000 | M46: =Operation!N50 -> 0
B47: Total Liabities | I47: =SUM(I44:I46) -> 10335342 | J47: =SUM(J44:J46) -> 9056072.9 | K47: =SUM(K44:K46) -> 7802942.8 | L47: =SUM(L44:L46) -> 6378061.1 | M47: =SUM(M44:M46) -> 4921402.9
B49: Retained Earnings | I49: =I29 -> 1279692 | J49: =J29 -> 2693884.6 | K49: =K29 -> 5221643.4 | L49: =L29 -> 8403171.5 | M49: =M29 -> 12153400
B50: Equity | I50: =I67 -> 7000000 | J50: =I50 -> 7000000 | K50: =J50 -> 7000000 | L50: =K50 -> 7000000 | M50: =L50 -> 7000000
B51: Total Liabilities & Equity | I51: =SUM(I47:I50) -> 18615034 | J51: =SUM(J47:J50) -> 18749957 | K51: =SUM(K47:K50) -> 20024586 | L51: =SUM(L47:L50) -> 21781233 | M51: =SUM(M47:M50) -> 24074803
B52: Check | I52: =I41-I51 -> 0 | J52: =J41-J51 -> 0 | K52: =K41-K51 -> 0 | L52: =L41-L51 -> 0 | M52: =M41-M51 -> 0
A54: Cashflow statement
B55: Net income | I55: =I23 -> 1505520 | J55: =J23 -> 1663756 | K55: =K23 -> 2973833.8 | L55: =L23 -> 3742974.3 | M55: =M23 -> 4412033.9
B56: Add: depreciation | I56: =I17 -> 2600000 | J56: =J17 -> 2600000 | K56: =K17 -> 2600000 | L56: =L17 -> 2600000 | M56: =M17 -> 2600000
B57: Changes in Trade Receivables | I57: =Operation!J69 -> -3698630.1 | J57: =Operation!K69 -> -184931.51 | K57: =Operation!L69 -> -316510.27 | L57: =Operation!M69 -> -159791.1 | M57: =Operation!N69 -> -130795.89
B58: Changes in Trade Inventory | I58: =Operation!J71 -> -2810958.9 | J58: =Operation!K71 -> -229093.15 | K58: =Operation!L71 -> -247764.24 | L58: =Operation!M71 -> -125084.47 | M58: =Operation!N71 -> -102387.02
B59: Changes in Trade Paybles | I59: =Operation!J73 -> 3935342.5 | J59: =Operation!K73 -> 320730.41 | K59: =Operation!L73 -> 346869.94 | L59: =Operation!M73 -> 175118.26 | M59: =Operation!N73 -> 143341.83
B60: Changes in Other assets | I60: 0 | J60: 0 | K60: 0 | L60: 0 | M60: 0
B61: Changes in Other Liabilities | I61: 0 | J61: 0 | K61: 0 | L61: 0 | M61: 0
B62: Operating Cash flow | I62: =SUM(I55:I61) -> 1531273.4 | J62: =SUM(J55:J61) -> 4170461.8 | K62: =SUM(K55:K61) -> 5356429.3 | L62: =SUM(L55:L61) -> 6233217 | M62: =SUM(M55:M61) -> 6922192.9
B64: Capex | I64: =-Operation!J63 -> -13000000 | J64: 0 | K64: 0 | L64: 0 | M64: 0
B65: Investing cashflow | I65: =SUM(I64) -> -13000000 | J65: =SUM(J64) -> 0 | K65: =SUM(K64) -> 0 | L65: =SUM(L64) -> 0 | M65: =SUM(M64) -> 0
B67: Capital Contribution | I67: =Operation!H42+Operation!H43 -> 7000000 | J67: 0 | K67: 0 | L67: 0 | M67: 0
B68: Debt issue | I68: =Operation!H41 -> 8000000 | J68: 0 | K68: 0 | L68: 0 | M68: 0
B69: Dividend | I69: =-I28 -> -225828 | J69: =-J28 -> -249563.4 | K69: =-K28 -> -446075.08 | L69: =-L28 -> -561446.15 | M69: =-M28 -> -661805.09
B70: debt repayment | I70: =-Operation!J49 -> -1600000 | J70: =-Operation!K49 -> -1600000 | K70: =-Operation!L49 -> -1600000 | L70: =-Operation!M49 -> -1600000 | M70: =-Operation!N49 -> -1600000
B71: Financing cashflow | I71: =SUM(I67:I70) -> 13174172 | J71: =SUM(J67:J70) -> -1849563.4 | K71: =SUM(K67:K70) -> -2046075.1 | L71: =SUM(L67:L70) -> -2161446.1 | M71: =SUM(M67:M70) -> -2261805.1
B73: Net Cash Flow | I73: =I62+I65+I71 -> 1705445.4 | J73: =J62+J65+J71 -> 2320898.4 | K73: =K62+K65+K71 -> 3310354.2 | L73: =L62+L65+L71 -> 4071770.9 | M73: =M62+M65+M71 -> 4660387.8
B74: Beginnig cash Bal | I74: 0 | J74: =I75 -> 1705445.4 | K74: =J75 -> 4026343.8 | L74: =K75 -> 7336698 | M74: =L75 -> 11408469
B75: Ending Cash Bal | I75: =SUM(I73:I74) -> 1705445.4 | J75: =SUM(J73:J74) -> 4026343.8 | K75: =SUM(K73:K74) -> 7336698 | L75: =SUM(L73:L74) -> 11408469 | M75: =SUM(M73:M74) -> 16068857
B78: Revolver
B79: Available Cash
B80: Beginning Cash Balance | I80: =I74 -> 0 | J80: =J74 -> 1705445.4 | K80: =K74 -> 4026343.8 | L80: =L74 -> 7336698 | M80: =M74 -> 11408469
B81: Cash from Operation | I81: =I62 -> 1531273.4 | J81: =J62 -> 4170461.8 | K81: =K62 -> 5356429.3 | L81: =L62 -> 6233217 | M81: =M62 -> 6922192.9
B82: Cash form Investing | I82: =I65 -> -13000000 | J82: 0 | K82: 0 | L82: 0 | M82: 0
B83: Capital Contribution | I83: =I67 -> 7000000
B84: Debt issue | I84: =I68 -> 8000000 | J84: =J68 -> 0 | K84: =K68 -> 0 | L84: =L68 -> 0 | M84: =M68 -> 0
B85: Debt repayement | I85: =I70 -> -1600000 | J85: =J70 -> -1600000 | K85: =K70 -> -1600000 | L85: =L70 -> -1600000 | M85: =M70 -> -1600000
B86: Dividend | I86: =I69 -> -225828 | J86: =J69 -> -249563.4 | K86: =K69 -> -446075.08 | L86: =L69 -> -561446.15 | M86: =M69 -> -661805.09
B87: Cash Available for revolver | I87: =SUM(I80:I86) -> 1705445.4 | J87: =SUM(J80:J86) -> 4026343.8 | K87: =SUM(K80:K86) -> 7336698 | L87: =SUM(L80:L86) -> 11408469 | M87: =SUM(M80:M86) -> 16068857
B89: Revolver
B91: Beginnig Balance | I91: 0 | J91: 0 | K91: 0 | L91: 0 | M91: 0
B92: Changes in Revolver | I92: 0 | J92: 0 | K92: 0 | L92: 0 | M92: 0
B93: Ending Balance | I93: =SUM(I91:I92) -> 0 | J93: =SUM(J91:J92) -> 0 | K93: =SUM(K91:K92) -> 0 | L93: =SUM(L91:L92) -> 0 | M93: =SUM(M91:M92) -> 0
B95: Revolver Interest | I95: 0.035 | J95: 0.035 | K95: 0.035 | L95: 0.035 | M95: 0.035
B96: Interest Expense | I96: 0 | J96: 0 | K96: 0 | L96: 0 | M96: 0
B97: Total Interest Expense | I97: =I96+Operation!J52 -> 1600000 | J97: =J96+Operation!K52 -> 1280000 | K97: =K96+Operation!L52 -> 960000 | L97: =L96+Operation!M52 -> 640000 | M97: =M96+Operation!N52 -> 320000

Sheet Calc>>
A1: =coyname -> ABC BOTTLE WATER | H1: years | I1: ='Cover page'!I14 -> 2025 | J1: =I1+1 -> 2026 | K1: =J1+1 -> 2027 | L1: =K1+1 -> 2028 | M1: =L1+1 -> 2029
A2: 3-statement Model | H2: Start date | I2: ='Cover page'!I16 -> 45658 | J2: =EDATE(I2,12) -> 46023 | K2: =EDATE(J2,12) -> 46388 | L2: =EDATE(K2,12) -> 46753 | M2: =EDATE(L2,12) -> 47119
A3: All figures are in #(Naira) | H3: End date | I3: =DATE(I1,12,31) -> 46022 | J3: =DATE(J1,12,31) -> 46387 | K3: =DATE(K1,12,31) -> 46752 | L3: =DATE(L1,12,31) -> 47118 | M3: =DATE(M1,12,31) -> 47483
H4: Year Counter | I4: 1 | J4: =I4+1 -> 2 | K4: =J4+1 -> 3 | L4: =K4+1 -> 4 | M4: =L4+1 -> 5

Sheet Operation
A1: =coyname -> ABC BOTTLE WATER | H1: years | J1: ='Cover page'!I14 -> 2025 | K1: =J1+1 -> 2026 | L1: =K1+1 -> 2027 | M1: =L1+1 -> 2028 | N1: =M1+1 -> 2029
A2: 3-statement Model | H2: Start date | J2: ='Cover page'!I16 -> 45658 | K2: =EDATE(J2,12) -> 46023 | L2: =EDATE(K2,12) -> 46388 | M2: =EDATE(L2,12) -> 46753 | N2: =EDATE(M2,12) -> 47119
A3: All figures are in #(Naira) | H3: End date | J3: =DATE(J1,12,31) -> 46022 | K3: =DATE(K1,12,31) -> 46387 | L3: =DATE(L1,12,31) -> 46752 | M3: =DATE(M1,12,31) -> 47118 | N3: =DATE(N1,12,31) -> 47483
H4: Year Counter | J4: 1 | K4: =J4+1 -> 2 | L4: =K4+1 -> 3 | M4: =L4+1 -> 4 | N4: =M4+1 -> 5
A6: 1 | B6: Revenue
D7: Capacity | H7: =Input!H19 -> 20000
D8: Quantity | H8: =Input!H20 -> 18000
D9: Growth | J9: 0 | K9: 0.05 | L9: 0.05 | M9: 0.05 | N9: 0.05
A10: a | B10: Total Quantity | J10: =H8*(1+J9) -> 18000 | K10: =J10*(1+K9) -> 18900 | L10: =K10*(1+L9) -> 19845 | M10: =IF(L10*(1+M9)>$H$7,$H$7,0) -> 20000 | N10: =IF(M10*(1+N9)>$H$7,$H$7,0) -> 20000
D11: Inflation | H11: =Input!H9 -> 0.03
A12: b | D12: Price per Quantity | J12: =Input!H12 -> 3000 | K12: =J12 -> 3000 | L12: =K12*(1+$H$11) -> 3090 | M12: =L12*(1+$H$11) -> 3182.7 | N12: =M12*(1+$H$11) -> 3278.181
B13: Total Revenue | E13: (a*b) | J13: =J10*J12 -> 54000000 | K13: =K10*K12 -> 56700000 | L13: =L10*L12 -> 61321050 | M13: =M10*M12 -> 63654000 | N13: =N10*N12 -> 65563620
A15: 2 | B15: Direct Cost
D16: Plastic Bottle cost | H16: =Input!H14 -> 1000
D17: Packing and Packaging | H17: =Input!H15 -> 500
D18: Labelling | H18: =Input!H16 -> 400
D19: Inflation | H19: =H11 -> 0.03
A20: a | C20: Direct cost | H20: =SUM(H16:H18) -> 1900 | J20: =H20 -> 1900 | K20: =J20*(1+$H$19) -> 1957 | L20: =K20*(1+$H$19) -> 2015.71 | M20: =L20*(1+$H$19) -> 2076.1813 | N20: =M20*(1+$H$19) -> 2138.4667
A21: b | B21: Total Quantity | J21: =J10 -> 18000 | K21: =K10 -> 18900 | L21: =L10 -> 19845 | M21: =M10 -> 20000 | N21: =N10 -> 20000
B22: Total Direct cost | E22: (a*b) | J22: =J20*J21 -> 34200000 | K22: =K20*K21 -> 36987300 | L22: =L20*L21 -> 40001765 | M22: =M20*M21 -> 41523626 | N22: =N20*N21 -> 42769335
A24: 3 | B24: Operating Expense
D25: Maintenance and repair | E25: =Input!E24 -> Months | H25: =Input!H24 -> 30000 | J25: =H25*Input!$H$7 -> 360000 | K25: =J25 -> 360000 | L25: =K25 -> 360000 | M25: =L25 -> 360000 | N25: =M25 -> 360000
D26: Transportation and distribution cost | E26: =Input!E25 -> Months | H26: =Input!H25 -> 50000 | J26: =H26*Input!$H$7 -> 600000 | K26: =J26 -> 600000 | L26: =K26 -> 600000 | M26: =L26 -> 600000 | N26: =M26 -> 600000
D27: Regulatory and compliance cost | E27: =Input!E26 -> Year | H27: =Input!H26 -> 60000 | J27: =H27 -> 60000 | K27: =J27 -> 60000 | L27: =K27 -> 60000 | M27: =L27 -> 60000 | N27: =M27 -> 60000
D28: Miscellaneous Costs | E28: =Input!E27 -> Year | H28: =Input!H27 -> 30000 | J28: =H28 -> 30000 | K28: =J28 -> 30000 | L28: =K28 -> 30000 | M28: =L28 -> 30000 | N28: =M28 -> 30000
D29: Water treatment cost | E29: =Input!E28 -> Months | H29: =Input!H28 -> 90000 | J29: =H29*Input!$H$7 -> 1080000 | K29: =J29 -> 1080000 | L29: =K29 -> 1080000 | M29: =L29 -> 1080000 | N29: =M29 -> 1080000
D30: Energy cost (Utility) | E30: =Input!E29 -> Months | H30: =Input!H29 -> 40000 | J30: =H30*Input!$H$7 -> 480000 | K30: =J30 -> 480000 | L30: =K30 -> 480000 | M30: =L30 -> 480000 | N30: =M30 -> 480000
C31: Salaries & Wages
D32: 1 Manager | E32: Months | F32: 1 | H32: =Input!H31 -> 180000 | J32: =H32*Input!$H$7*F32 -> 2160000 | K32: =J32 -> 2160000 | L32: =K32 -> 2160000 | M32: =L32 -> 2160000 | N32: =M32 -> 2160000
D33: 1 Supervisor | E33: Months | F33: 1 | H33: =Input!H32 -> 130000 | J33: =H33*F33*Input!H7 -> 1560000 | K33: =J33 -> 1560000 | L33: =K33 -> 1560000 | M33: =L33 -> 1560000 | N33: =M33 -> 1560000
D34: 2 sales representatives | E34: Months | F34: 2 | H34: =Input!H33 -> 50000 | J34: =H34*F34*Input!$H$7 -> 1200000 | K34: =J34 -> 1200000 | L34: =K34 -> 1200000 | M34: =L34 -> 1200000 | N34: =M34 -> 1200000
D35: Factory guard | E35: Months | F35: 1 | H35: =Input!H34 -> 20000 | J35: =H35*F35*Input!$H$7 -> 240000 | K35: =J35 -> 240000 | L35: =K35 -> 240000 | M35: =L35 -> 240000 | N35: =M35 -> 240000
D36: 3 senior Factory workers | E36: Months | F36: 3 | H36: =Input!H35 -> 65000 | J36: =H36*F36*Input!$H$7 -> 2340000 | K36: =J36 -> 2340000 | L36: =K36 -> 2340000 | M36: =L36 -> 2340000 | N36: =M36 -> 2340000
D37: 7 Staff on daily wages payment | E37: 6 | F37: 7 | H37: =Input!H36 -> 1500 | J37: =H37*F37*E37*Input!H8 -> 3276000 | K37: =J37 -> 3276000 | L37: =K37 -> 3276000 | M37: =L37 -> 3276000 | N37: =M37 -> 3276000
C38: Total Operating Expenses | J38: =SUM(J25:J37) -> 13386000 | K38: =SUM(K25:K37) -> 13386000 | L38: =SUM(L25:L37) -> 13386000 | M38: =SUM(M25:M37) -> 13386000 | N38: =SUM(N25:N37) -> 13386000
A40: 4 | B40: Source of Funding
D41: Long Term debt | H41: =Input!H40 -> 8000000
D42: Equity | H42: =Input!H41 -> 3000000
D43: Personal contribution | H43: =Input!H42 -> 4000000
C44: Total | H44: =SUM(H41:H43) -> 15000000
A46: 5 | B46: Debt Schedule
D47: Opening Bals | J47: 0 | K47: =J50 -> 6400000 | L47: =K50 -> 4800000 | M47: =L50 -> 3200000 | N47: =M50 -> 1600000
D48: Additions | J48: =H41 -> 8000000 | K48: 0 | L48: 0 | M48: 0 | N48: 0
D49: Repayment | J49: =$J$48/Input!$H$53 -> 1600000 | K49: =$J$48/Input!$H$53 -> 1600000 | L49: =$J$48/Input!$H$53 -> 1600000 | M49: =$J$48/Input!$H$53 -> 1600000 | N49: =$J$48/Input!$H$53 -> 1600000
D50: Closing Bals | J50: =J47+J48-J49 -> 6400000 | K50: =K47+K48-K49 -> 4800000 | L50: =L47+L48-L49 -> 3200000 | M50: =M47+M48-M49 -> 1600000 | N50: 0
D52: Interest | H52: =Input!H45 -> 0.2 | J52: =MAX(J47:J48)*$H$52 -> 1600000 | K52: =MAX(K47:K48)*$H$52 -> 1280000 | L52: =MAX(L47:L48)*$H$52 -> 960000 | M52: =MAX(M47:M48)*$H$52 -> 640000 | N52: =MAX(N47:N48)*$H$52 -> 320000
A54: 6 | B54: Use of Fund
D55: Water Source | H55: =Input!H49 -> 700000
D56: Motor Vehicle | H56: =Input!H50 -> 8000000
D57: Bottling and Packaging Machinery | H57: =Input!H51 -> 3000000
D58: Water Storage Tanks | H58: =Input!H52 -> 1300000
D59: Total PPE | H59: =SUM(H55:H58) -> 13000000
A61: 7 | B61: PPE Schedule
D62: Opening Bals | J62: 0 | K62: =J65 -> 10400000 | L62: =K65 -> 7800000 | M62: =L65 -> 5200000 | N62: =M65 -> 2600000
D63: Capex | J63: =H59 -> 13000000 | K63: 0 | L63: 0 | M63: 0 | N63: 0
D64: Depreciation | G64: =Input!H54 -> 0.2 | J64: =J63*G64 -> 2600000 | K64: =J64 -> 2600000 | L64: =K64 -> 2600000 | M64: =L64 -> 2600000 | N64: =M64 -> 2600000
C65: Closing Bals | J65: =J62+J63-J64 -> 10400000 | K65: =K62+K63-K64 -> 7800000 | L65: =L62+L63-L64 -> 5200000 | M65: =M62+M63-M64 -> 2600000 | N65: =N62+N63-N64 -> 0
A67: 8 | B67: Working Capital
D68: Account receivables | J68: =Input!$H$58/Input!$H$6*Operation!J13 -> 3698630.1 | K68: =Input!$H$58/Input!$H$6*Operation!K13 -> 3883561.6 | L68: =Input!$H$58/Input!$H$6*Operation!L13 -> 4200071.9 | M68: =Input!$H$58/Input!$H$6*Operation!M13 -> 4359863 | N68: =Input!$H$58/Input!$H$6*Operation!N13 -> 4490658.9
D69: Movement | J69: =I68-J68 -> -3698630.1 | K69: =J68-K68 -> -184931.51 | L69: =K68-L68 -> -316510.27 | M69: =L68-M68 -> -159791.1 | N69: =M68-N68 -> -130795.89
D70: Inventory | J70: =Input!$H$57/Input!$H$6*Operation!J22 -> 2810958.9 | K70: =Input!$H$57/Input!$H$6*Operation!K22 -> 3040052.1 | L70: =Input!$H$57/Input!$H$6*Operation!L22 -> 3287816.3 | M70: =Input!$H$57/Input!$H$6*Operation!M22 -> 3412900.8 | N70: =Input!$H$57/Input!$H$6*Operation!N22 -> 3515287.8
D71: Movement | J71: =I70-J70 -> -2810958.9 | K71: =J70-K70 -> -229093.15 | L71: =K70-L70 -> -247764.24 | M71: =L70-M70 -> -125084.47 | N71: =M70-N70 -> -102387.02
D72: Account Payables | J72: =Input!$H$59/Input!$H$6*Operation!J22 -> 3935342.5 | K72: =Input!$H$59/Input!$H$6*Operation!K22 -> 4256072.9 | L72: =Input!$H$59/Input!$H$6*Operation!L22 -> 4602942.8 | M72: =Input!$H$59/Input!$H$6*Operation!M22 -> 4778061.1 | N72: =Input!$H$59/Input!$H$6*Operation!N22 -> 4921402.9
D73: Movement | J73: =J72-I72 -> 3935342.5 | K73: =K72-J72 -> 320730.41 | L73: =L72-K72 -> 346869.94 | M73: =M72-L72 -> 175118.26 | N73: =N72-M72 -> 143341.83
A75: 9 | B75: Taxation | G75: 0.32
D76: Earnings before Tax | J76: =FS!I21 -> 2214000 | K76: =FS!J21 -> 2446700 | L76: =FS!K21 -> 4373285 | M76: =FS!L21 -> 5504374 | N76: =FS!M21 -> 6488285.2
D77: Taxes | J77: =J76*$G$75 -> 708480 | K77: =K76*$G$75 -> 782944 | L77: =L76*$G$75 -> 1399451.2 | M77: =M76*$G$75 -> 1761399.7 | N77: =N76*$G$75 -> 2076251.3
A79: 10 | B79: Dividend | G79: 0.15
D80: Net Earnings | J80: =FS!I23 -> 1505520 | K80: =FS!J23 -> 1663756 | L80: =FS!K23 -> 2973833.8 | M80: =FS!L23 -> 3742974.3 | N80: =FS!M23 -> 4412033.9
D81: Dividend | J81: =J80*$G$79 -> 225828 | K81: =K80*$G$79 -> 249563.4 | L81: =L80*$G$79 -> 446075.08 | M81: =M80*$G$79 -> 561446.15 | N81: =N80*$G$79 -> 661805.09

Sheet Analysis
A1: =coyname -> ABC BOTTLE WATER | H1: years | I1: ='Cover page'!I14 -> 2025 | J1: =I1+1 -> 2026 | K1: =J1+1 -> 2027 | L1: =K1+1 -> 2028 | M1: =L1+1 -> 2029
A2: 3-statement Model | H2: Start date | I2: ='Cover page'!I16 -> 45658 | J2: =EDATE(I2,12) -> 46023 | K2: =EDATE(J2,12) -> 46388 | L2: =EDATE(K2,12) -> 46753 | M2: =EDATE(L2,12) -> 47119
A3: All figures are in #(Naira) | H3: End date | I3: =DATE(I1,12,31) -> 46022 | J3: =DATE(J1,12,31) -> 46387 | K3: =DATE(K1,12,31) -> 46752 | L3: =DATE(L1,12,31) -> 47118 | M3: =DATE(M1,12,31) -> 47483
H4: Year Counter | I4: 1 | J4: =I4+1 -> 2 | K4: =J4+1 -> 3 | L4: =K4+1 -> 4 | M4: =L4+1 -> 5

Sheet Ratio
A1: =coyname -> ABC BOTTLE WATER | I1: years | J1: ='Cover page'!I14 -> 2025 | K1: =J1+1 -> 2026 | L1: =K1+1 -> 2027 | M1: =L1+1 -> 2028 | N1: =M1+1 -> 2029
A2: 3-statement Model | I2: Start date | J2: ='Cover page'!I16 -> 45658 | K2: =EDATE(J2,12) -> 46023 | L2: =EDATE(K2,12) -> 46388 | M2: =EDATE(L2,12) -> 46753 | N2: =EDATE(M2,12) -> 47119
A3: All figures are in #(Naira) | I3: End date | J3: =DATE(J1,12,31) -> 46022 | K3: =DATE(K1,12,31) -> 46387 | L3: =DATE(L1,12,31) -> 46752 | M3: =DATE(M1,12,31) -> 47118 | N3: =DATE(N1,12,31) -> 47483
I4: Year Counter | J4: 1 | K4: =J4+1 -> 2 | L4: =K4+1 -> 3 | M4: =L4+1 -> 4 | N4: =M4+1 -> 5
B6: Ratio Analysis
B7: Profitability Ratios
D9: Return on Equity | E9: = | F9: Net Income | J9: =FS!I23 -> 1505520 | K9: =FS!J23 -> 1663756 | L9: =FS!K23 -> 2973833.8 | M9: =FS!L23 -> 3742974.3 | N9: =FS!M23 -> 4412033.9
F10: Equity | J10: =FS!I49+FS!I50 -> 8279692 | K10: =FS!J49+FS!J50 -> 9693884.6 | L10: =FS!K49+FS!K50 -> 12221643 | M10: =FS!L49+FS!L50 -> 15403172 | N10: =FS!M49+FS!M50 -> 19153400
J11: =J9/J10 -> 0.18183285 | K11: =K9/K10 -> 0.17162944 | L11: =L9/L10 -> 0.2433252 | M11: =M9/M10 -> 0.24300024 | N11: =N9/N10 -> 0.23035251
D13: Return on Assets | E13: = | F13: Net Income
F14: Total Assets

Sheet Model>>
A1: =coyname -> ABC BOTTLE WATER | H1: years | I1: ='Cover page'!I14 -> 2025 | J1: =I1+1 -> 2026 | K1: =J1+1 -> 2027 | L1: =K1+1 -> 2028 | M1: =L1+1 -> 2029
A2: 3-statement Model | H2: Start date | I2: ='Cover page'!I16 -> 45658 | J2: =EDATE(I2,12) -> 46023 | K2: =EDATE(J2,12) -> 46388 | L2: =EDATE(K2,12) -> 46753 | M2: =EDATE(L2,12) -> 47119
A3: All figures are in #(Naira) | H3: End date | I3: =DATE(I1,12,31) -> 46022 | J3: =DATE(J1,12,31) -> 46387 | K3: =DATE(K1,12,31) -> 46752 | L3: =DATE(L1,12,31) -> 47118 | M3: =DATE(M1,12,31) -> 47483
H4: Year Counter | I4: 1 | J4: =I4+1 -> 2 | K4: =J4+1 -> 3 | L4: =K4+1 -> 4 | M4: =L4+1 -> 5

Sheet Input
A1: =coyname -> ABC BOTTLE WATER | H1: years | I1: ='Cover page'!I14 -> 2025 | J1: =I1+1 -> 2026 | K1: =J1+1 -> 2027 | L1: =K1+1 -> 2028 | M1: =L1+1 -> 2029
A2: 3-statement Model | H2: Start date | I2: ='Cover page'!I16 -> 45658 | J2: =EDATE(I2,12) -> 46023 | K2: =EDATE(J2,12) -> 46388 | L2: =EDATE(K2,12) -> 46753 | M2: =EDATE(L2,12) -> 47119
A3: All figures are in #(Naira) | H3: End date | I3: =DATE(I1,12,31) -> 46022 | J3: =DATE(J1,12,31) -> 46387 | K3: =DATE(K1,12,31) -> 46752 | L3: =DATE(L1,12,31) -> 47118 | M3: =DATE(M1,12,31) -> 47483
H4: Year Counter | I4: 1 | J4: =I4+1 -> 2 | K4: =J4+1 -> 3 | L4: =K4+1 -> 4 | M4: =L4+1 -> 5
A5: General asumptions
B6: Days in a year | H6: 365
B7: Months in a year | H7: 12
B8: Weeks in a year | H8: 52
B9: Inflation | H9: 0.03
A11: princing
B12: Selling price per pack | H12: 3000
B13: Direct cost
C14: Plastic Bottle cost | H14: 1000
C15: Packing and Packaging | H15: 500
C16: Labelling | H16: 400
A18: Volume and Quantity
B19: Capacity | H19: 20000
B20: Quantity | H20: 18000
B21: Growth | H21: 0.05
A23: Operational Exepenses
B24: Maintenance and repair | E24: Months | H24: 30000
B25: Transportation and distribution cost | E25: Months | H25: 50000
B26: Regulatory and compliance cost | E26: Year | H26: 60000
B27: Miscellaneous Costs | E27: Year | H27: 30000
B28: Water treatment cost | E28: Months | H28: 90000
B29: Energy cost (Utility) | E29: Months | H29: 40000
B30: Salary & wages
C31: 1 Manager | E31: Months | H31: 180000
C32: 1 Supervisor | E32: Months | H32: 130000
C33: 2 sales representatives | E33: Months | H33: 50000
C34: Factory guard | E34: Months | H34: 20000
C35: 3 senior Factory workers | E35: Months | H35: 65000
C36: 7 Staff on daily wages payment | E36: 6 days per week | H36: 1500
A38: Funding
B39: Source of Fund
C40: Long Term debt | H40: 8000000
C41: Equity | H41: 3000000
C42: Personal contribution | H42: 4000000
C43: Revolving credit for additional funding | H43: 0.035
C44: Loan Repayment Period | H44: 5
C45: Interest rate | H45: 0.2
C46: Dividend | H46: 0.15
A48: Property,Plant&Equipment
C49: Water Source | H49: 700000
C50: Motor Vehicle | H50: 8000000
C51: Bottling and Packaging Machinery | H51: 3000000
C52: Water Storage Tanks | H52: 1300000
C53: Estimated year | H53: 5
C54: Depreciation Rate | H54: 0.2
A56: Working Capital
C57: Inventory Days | E57: Days | H57: 30
C58: Receivable Days | E58: Days | H58: 25
C59: Payables Days | E59: Days | H59: 42
